{
  "$description": "Frozen HTTP wire contract for @qlan-ro/mainframe-core. Generated by scripts/extract-contract.mjs — do not hand-edit.",
  "generator": "packages/core/scripts/extract-contract.mjs",
  "method": "HTTP routes enumerated by walking the live Express router stack (each factory mounted with a Proxy ctx); per-endpoint request schema, response shape, and status codes derived by TypeScript-AST analysis of src/server/routes/*.ts.",
  "authModel": {
    "secretEnv": "AUTH_TOKEN_SECRET",
    "whenSecretUnset": "middleware is a no-op; all routes are unauthenticated",
    "publicPaths": ["/health", "/api/auth/confirm", "/api/auth/status", "/api/auth/pair-status"],
    "scheme": "Authorization: Bearer <device token>",
    "loopbackBypass": {
      "ips": ["127.0.0.1", "::1", "::ffff:127.0.0.1"],
      "behavior": "loopback callers are never rejected; token is validated and attached only if present"
    },
    "onReject": {
      "status": 401,
      "body": {
        "success": false,
        "error": "Unauthorized"
      }
    },
    "websocket": {
      "tokenSource": "token query param on the upgrade URL",
      "loopbackBypass": true,
      "onReject": "HTTP/1.1 401 Unauthorized then socket destroyed",
      "forwardedFor": "x-forwarded-for first hop is trusted only when the raw peer is loopback (cloudflared)"
    }
  },
  "envelopeShapes": {
    "ok": {
      "success": true,
      "data": "<T>"
    },
    "okEmpty": {
      "success": true
    },
    "fail": {
      "success": false,
      "error": "<string>"
    },
    "helper": "src/server/routes/respond.ts (ok / okEmpty / fail)"
  },
  "globalBehaviors": {
    "cors": "Access-Control-Allow-Origin echoed for http(s)://localhost|127.0.0.1(:port); OPTIONS → 204",
    "bodyLimit": "30mb JSON (express.json)",
    "unhandledError": {
      "status": 500,
      "body": {
        "success": false,
        "error": "Internal server error"
      }
    },
    "securityHeaders": ["X-Content-Type-Options: nosniff"]
  },
  "knownDeviations": [
    "DELETE /api/tags/:name returns bare 204 (no envelope).",
    "GET /health returns a bare status object, not the {success,data} envelope.",
    "POST /api/projects returns 409 with a data payload alongside success:false on duplicate."
  ],
  "dynamicMounts": [
    {
      "method": "*",
      "path": "/api/plugins/*",
      "auth": {
        "requirement": "bearer",
        "loopbackBypass": true
      },
      "request": null,
      "response": {
        "note": "per-plugin; PluginManager.router owns a listing route plus one sub-router per plugin"
      },
      "statusCodes": [],
      "confidence": "low",
      "notes": "Dynamic mount (src/server/http.ts: app.use(\"/api/plugins\", pluginManager.router)). Builtin plugins (todos) register sub-routes at runtime; not enumerable from a static router walk. Rust v1 keeps builtins behind this surface."
    }
  ],
  "routeCount": 129,
  "routes": [
    {
      "method": "GET",
      "path": "/api/adapters",
      "auth": {
        "requirement": "bearer",
        "loopbackBypass": true
      },
      "request": null,
      "response": {
        "envelope": "hand-rolled-json",
        "kinds": ["json"]
      },
      "statusCodes": [200],
      "sourceFile": "src/server/routes/adapters.ts",
      "confidence": "high"
    },
    {
      "method": "GET",
      "path": "/api/adapters/:adapterId/agents",
      "auth": {
        "requirement": "bearer",
        "loopbackBypass": true
      },
      "request": {
        "jsonSchema": {
          "$schema": "https://json-schema.org/draft/2020-12/schema",
          "type": "object",
          "properties": {
            "projectPath": {
              "type": "string",
              "minLength": 1
            }
          },
          "required": ["projectPath"]
        },
        "source": "schemas.ts:ProjectPathQuery"
      },
      "response": {
        "envelope": "hand-rolled-json",
        "kinds": ["json"]
      },
      "statusCodes": [200, 400, 404],
      "sourceFile": "src/server/routes/agents.ts",
      "confidence": "high"
    },
    {
      "method": "POST",
      "path": "/api/adapters/:adapterId/agents",
      "auth": {
        "requirement": "bearer",
        "loopbackBypass": true
      },
      "request": {
        "jsonSchema": {
          "$schema": "https://json-schema.org/draft/2020-12/schema",
          "type": "object",
          "properties": {
            "projectPath": {
              "type": "string",
              "minLength": 1
            },
            "name": {
              "type": "string",
              "minLength": 1,
              "pattern": "^[a-zA-Z0-9_-]+$"
            },
            "description": {
              "type": "string"
            },
            "content": {
              "type": "string"
            },
            "scope": {
              "type": "string",
              "enum": ["project", "global"]
            }
          },
          "required": ["projectPath", "name"]
        },
        "source": "schemas.ts:CreateAgentBody"
      },
      "response": {
        "envelope": "hand-rolled-json",
        "kinds": ["json"]
      },
      "statusCodes": [200, 400, 404, 500],
      "sourceFile": "src/server/routes/agents.ts",
      "confidence": "high"
    },
    {
      "method": "DELETE",
      "path": "/api/adapters/:adapterId/agents/:id",
      "auth": {
        "requirement": "bearer",
        "loopbackBypass": true
      },
      "request": {
        "jsonSchema": {
          "$schema": "https://json-schema.org/draft/2020-12/schema",
          "type": "object",
          "properties": {
            "projectPath": {
              "type": "string",
              "minLength": 1
            }
          },
          "required": ["projectPath"]
        },
        "source": "schemas.ts:ProjectPathQuery"
      },
      "response": {
        "envelope": "hand-rolled-json",
        "kinds": ["json"]
      },
      "statusCodes": [200, 400, 404, 500],
      "sourceFile": "src/server/routes/agents.ts",
      "confidence": "high"
    },
    {
      "method": "PUT",
      "path": "/api/adapters/:adapterId/agents/:id",
      "auth": {
        "requirement": "bearer",
        "loopbackBypass": true
      },
      "request": {
        "jsonSchema": {
          "$schema": "https://json-schema.org/draft/2020-12/schema",
          "type": "object",
          "properties": {
            "projectPath": {
              "type": "string",
              "minLength": 1
            },
            "content": {
              "type": "string"
            }
          },
          "required": ["projectPath", "content"]
        },
        "source": "schemas.ts:UpdateAgentBody"
      },
      "response": {
        "envelope": "hand-rolled-json",
        "kinds": ["json"]
      },
      "statusCodes": [200, 400, 404, 500],
      "sourceFile": "src/server/routes/agents.ts",
      "confidence": "high"
    },
    {
      "method": "GET",
      "path": "/api/adapters/:adapterId/config-conflicts",
      "auth": {
        "requirement": "bearer",
        "loopbackBypass": true
      },
      "request": null,
      "response": {
        "envelope": "hand-rolled-json",
        "kinds": ["json"]
      },
      "statusCodes": [200],
      "sourceFile": "src/server/routes/settings.ts",
      "confidence": "high"
    },
    {
      "method": "GET",
      "path": "/api/adapters/:adapterId/skills",
      "auth": {
        "requirement": "bearer",
        "loopbackBypass": true
      },
      "request": {
        "jsonSchema": {
          "$schema": "https://json-schema.org/draft/2020-12/schema",
          "type": "object",
          "properties": {
            "projectPath": {
              "type": "string",
              "minLength": 1
            }
          },
          "required": ["projectPath"]
        },
        "source": "schemas.ts:ProjectPathQuery"
      },
      "response": {
        "envelope": "hand-rolled-json",
        "kinds": ["json"]
      },
      "statusCodes": [200, 400, 404],
      "sourceFile": "src/server/routes/skills.ts",
      "confidence": "high"
    },
    {
      "method": "POST",
      "path": "/api/adapters/:adapterId/skills",
      "auth": {
        "requirement": "bearer",
        "loopbackBypass": true
      },
      "request": {
        "jsonSchema": {
          "$schema": "https://json-schema.org/draft/2020-12/schema",
          "type": "object",
          "properties": {
            "projectPath": {
              "type": "string",
              "minLength": 1
            },
            "name": {
              "type": "string",
              "minLength": 1,
              "pattern": "^[a-zA-Z0-9_-]+$"
            },
            "displayName": {
              "type": "string"
            },
            "description": {
              "type": "string"
            },
            "content": {
              "type": "string"
            },
            "scope": {
              "type": "string",
              "enum": ["project", "global"]
            }
          },
          "required": ["projectPath", "name"]
        },
        "source": "schemas.ts:CreateSkillBody"
      },
      "response": {
        "envelope": "hand-rolled-json",
        "kinds": ["json"]
      },
      "statusCodes": [200, 400, 404, 500],
      "sourceFile": "src/server/routes/skills.ts",
      "confidence": "high"
    },
    {
      "method": "DELETE",
      "path": "/api/adapters/:adapterId/skills/:id",
      "auth": {
        "requirement": "bearer",
        "loopbackBypass": true
      },
      "request": {
        "jsonSchema": {
          "$schema": "https://json-schema.org/draft/2020-12/schema",
          "type": "object",
          "properties": {
            "projectPath": {
              "type": "string",
              "minLength": 1
            }
          },
          "required": ["projectPath"]
        },
        "source": "schemas.ts:ProjectPathQuery"
      },
      "response": {
        "envelope": "hand-rolled-json",
        "kinds": ["json"]
      },
      "statusCodes": [200, 400, 404, 500],
      "sourceFile": "src/server/routes/skills.ts",
      "confidence": "high"
    },
    {
      "method": "PUT",
      "path": "/api/adapters/:adapterId/skills/:id",
      "auth": {
        "requirement": "bearer",
        "loopbackBypass": true
      },
      "request": {
        "jsonSchema": {
          "$schema": "https://json-schema.org/draft/2020-12/schema",
          "type": "object",
          "properties": {
            "projectPath": {
              "type": "string",
              "minLength": 1
            },
            "content": {
              "type": "string"
            }
          },
          "required": ["projectPath", "content"]
        },
        "source": "schemas.ts:UpdateSkillBody"
      },
      "response": {
        "envelope": "hand-rolled-json",
        "kinds": ["json"]
      },
      "statusCodes": [200, 400, 404, 500],
      "sourceFile": "src/server/routes/skills.ts",
      "confidence": "high"
    },
    {
      "method": "POST",
      "path": "/api/auth/confirm",
      "auth": {
        "requirement": "none",
        "loopbackBypass": false
      },
      "request": {
        "name": "confirmBodySchema",
        "zodSource": "z.object({\n  pairingCode: z.string().min(1),\n  deviceName: z.string().min(1).optional(),\n  clientDeviceId: z.string().regex(/^[0-9a-f]{8}-[0-9a-f]{4}-[1-5][0-9a-f]{3}-[89ab][0-9a-f]{3}-[0-9a-f]{12}$/i),\n})",
        "source": "src/server/routes/auth.ts:confirmBodySchema",
        "note": "inline module-local Zod schema"
      },
      "response": {
        "envelope": "hand-rolled-json",
        "kinds": ["json"]
      },
      "statusCodes": [200, 400, 401, 429],
      "sourceFile": "src/server/routes/auth.ts",
      "confidence": "medium",
      "via": "delegated handler"
    },
    {
      "method": "GET",
      "path": "/api/auth/devices",
      "auth": {
        "requirement": "bearer",
        "loopbackBypass": true
      },
      "request": null,
      "response": {
        "envelope": "hand-rolled-json",
        "kinds": ["json"]
      },
      "statusCodes": [200],
      "sourceFile": "src/server/routes/auth.ts",
      "confidence": "high"
    },
    {
      "method": "DELETE",
      "path": "/api/auth/devices/:deviceId",
      "auth": {
        "requirement": "bearer",
        "loopbackBypass": true
      },
      "request": null,
      "response": {
        "envelope": "hand-rolled-json",
        "kinds": ["json"]
      },
      "statusCodes": [200],
      "sourceFile": "src/server/routes/auth.ts",
      "confidence": "high"
    },
    {
      "method": "POST",
      "path": "/api/auth/pair",
      "auth": {
        "requirement": "bearer",
        "loopbackBypass": true
      },
      "request": null,
      "response": {
        "envelope": "hand-rolled-json",
        "kinds": ["json"]
      },
      "statusCodes": [200, 400],
      "sourceFile": "src/server/routes/auth.ts",
      "confidence": "high",
      "via": "delegated handler"
    },
    {
      "method": "GET",
      "path": "/api/auth/pair-status",
      "auth": {
        "requirement": "none",
        "loopbackBypass": false
      },
      "request": {
        "name": "pairStatusQuerySchema",
        "zodSource": "z.object({ code: z.string().regex(/^[A-Z0-9]{6}$/) })",
        "source": "src/server/routes/auth.ts:pairStatusQuerySchema",
        "note": "inline module-local Zod schema"
      },
      "response": {
        "envelope": "hand-rolled-json",
        "kinds": ["json"]
      },
      "statusCodes": [200, 400],
      "sourceFile": "src/server/routes/auth.ts",
      "confidence": "medium",
      "via": "delegated handler"
    },
    {
      "method": "POST",
      "path": "/api/auth/register-push",
      "auth": {
        "requirement": "bearer",
        "loopbackBypass": true
      },
      "request": {
        "name": "registerPushSchema",
        "zodSource": "z.object({\n  deviceId: z.string().min(1),\n  pushToken: z.string().min(1),\n})",
        "source": "src/server/routes/auth.ts:registerPushSchema",
        "note": "inline module-local Zod schema"
      },
      "response": {
        "envelope": "hand-rolled-json",
        "kinds": ["json"]
      },
      "statusCodes": [200, 400, 401, 403],
      "sourceFile": "src/server/routes/auth.ts",
      "confidence": "medium"
    },
    {
      "method": "GET",
      "path": "/api/auth/status",
      "auth": {
        "requirement": "none",
        "loopbackBypass": false
      },
      "request": null,
      "response": {
        "envelope": "hand-rolled-json",
        "kinds": ["json"]
      },
      "statusCodes": [200],
      "sourceFile": "src/server/routes/auth.ts",
      "confidence": "high"
    },
    {
      "method": "GET",
      "path": "/api/chats",
      "auth": {
        "requirement": "bearer",
        "loopbackBypass": true
      },
      "request": {
        "name": "ListQuery",
        "zodSource": "z.object({\n    project: z.string().optional(),\n    tags: z\n      .string()\n      .optional()\n      .refine(\n        (v) =>\n          v === undefined ||\n          v\n            .split(',')\n            .map((s) => s.trim())\n            .filter(Boolean)\n            .every((t) => TAG_NAME_PATTERN.test(t)),\n        { message: 'Tag values must match [a-z0-9-]+' },\n      ),\n    synthetic: z.string().optional(),\n  })",
        "source": "src/server/routes/chats.ts:ListQuery",
        "note": "inline module-local Zod schema"
      },
      "response": {
        "envelope": "hand-rolled-json",
        "kinds": ["json"]
      },
      "statusCodes": [200, 400],
      "sourceFile": "src/server/routes/chats.ts",
      "confidence": "medium"
    },
    {
      "method": "POST",
      "path": "/api/chats",
      "auth": {
        "requirement": "bearer",
        "loopbackBypass": true
      },
      "request": {
        "jsonSchema": {
          "$schema": "https://json-schema.org/draft/2020-12/schema",
          "type": "object",
          "properties": {
            "projectId": {
              "type": "string",
              "minLength": 1
            },
            "adapterId": {
              "type": "string",
              "minLength": 1
            },
            "model": {
              "type": "string"
            },
            "permissionMode": {
              "type": "string",
              "enum": ["default", "acceptEdits", "yolo"]
            },
            "worktreePath": {
              "type": "string",
              "minLength": 1
            },
            "branchName": {
              "type": "string",
              "minLength": 1
            }
          },
          "required": ["projectId", "adapterId"]
        },
        "source": "ws-schemas.ts:CreateChatBody"
      },
      "response": {
        "envelope": "canonical-helpers",
        "kinds": ["envelope:fail", "envelope:ok"]
      },
      "statusCodes": [200, 400, 500],
      "sourceFile": "src/server/routes/chat-commands.ts",
      "confidence": "high"
    },
    {
      "method": "GET",
      "path": "/api/chats/:chatId/attachments/:attachmentId",
      "auth": {
        "requirement": "bearer",
        "loopbackBypass": true
      },
      "request": null,
      "response": {
        "envelope": "hand-rolled-json",
        "kinds": ["envelope:ok", "json"]
      },
      "statusCodes": [200, 404, 500],
      "sourceFile": "src/server/routes/attachments.ts",
      "confidence": "high"
    },
    {
      "method": "GET",
      "path": "/api/chats/:chatId/background-tasks",
      "auth": {
        "requirement": "bearer",
        "loopbackBypass": true
      },
      "request": {
        "name": "Params",
        "zodSource": "z.object({\n  chatId: z.string().min(1),\n  taskId: z.string().min(1).optional(),\n})",
        "source": "src/server/routes/background-tasks.ts:Params",
        "note": "inline module-local Zod schema"
      },
      "response": {
        "envelope": "canonical-helpers",
        "kinds": ["envelope:fail", "envelope:ok"]
      },
      "statusCodes": [200, 400],
      "sourceFile": "src/server/routes/background-tasks.ts",
      "confidence": "medium",
      "via": "delegated handler"
    },
    {
      "method": "POST",
      "path": "/api/chats/:chatId/background-tasks/:taskId/kill",
      "auth": {
        "requirement": "bearer",
        "loopbackBypass": true
      },
      "request": {
        "name": "Params",
        "zodSource": "z.object({\n  chatId: z.string().min(1),\n  taskId: z.string().min(1).optional(),\n})",
        "source": "src/server/routes/background-tasks.ts:Params",
        "note": "inline module-local Zod schema"
      },
      "response": {
        "envelope": "canonical-helpers",
        "kinds": ["envelope:fail", "envelope:okEmpty"]
      },
      "statusCodes": [200, 400, 404, 502],
      "sourceFile": "src/server/routes/background-tasks.ts",
      "confidence": "medium",
      "via": "delegated handler"
    },
    {
      "method": "GET",
      "path": "/api/chats/:chatId/background-tasks/:taskId/output",
      "auth": {
        "requirement": "bearer",
        "loopbackBypass": true
      },
      "request": {
        "name": "Params",
        "zodSource": "z.object({\n  chatId: z.string().min(1),\n  taskId: z.string().min(1).optional(),\n})",
        "source": "src/server/routes/background-tasks.ts:Params",
        "note": "inline module-local Zod schema"
      },
      "response": {
        "envelope": "raw",
        "kinds": ["envelope:fail", "raw-send"]
      },
      "statusCodes": [400, 404, 409, 500],
      "sourceFile": "src/server/routes/background-tasks.ts",
      "confidence": "medium",
      "via": "delegated handler"
    },
    {
      "method": "GET",
      "path": "/api/chats/:id",
      "auth": {
        "requirement": "bearer",
        "loopbackBypass": true
      },
      "request": null,
      "response": {
        "envelope": "hand-rolled-json",
        "kinds": ["json"]
      },
      "statusCodes": [200, 404],
      "sourceFile": "src/server/routes/chats.ts",
      "confidence": "high"
    },
    {
      "method": "POST",
      "path": "/api/chats/:id/archive",
      "auth": {
        "requirement": "bearer",
        "loopbackBypass": true
      },
      "request": null,
      "response": {
        "envelope": "hand-rolled-json",
        "kinds": ["json"]
      },
      "statusCodes": [200, 404],
      "sourceFile": "src/server/routes/chats.ts",
      "confidence": "high"
    },
    {
      "method": "POST",
      "path": "/api/chats/:id/attach-worktree",
      "auth": {
        "requirement": "bearer",
        "loopbackBypass": true
      },
      "request": {
        "name": "AttachWorktreeBody",
        "zodSource": "z.object({\n  worktreePath: z.string().min(1, 'Worktree path is required'),\n  branchName: z.string().min(1, 'Branch name is required'),\n})",
        "source": "src/server/routes/worktree.ts:AttachWorktreeBody",
        "note": "inline module-local Zod schema"
      },
      "response": {
        "envelope": "canonical-helpers",
        "kinds": ["envelope:fail", "envelope:okEmpty"]
      },
      "statusCodes": [200, 400],
      "sourceFile": "src/server/routes/worktree.ts",
      "confidence": "medium"
    },
    {
      "method": "POST",
      "path": "/api/chats/:id/attachments",
      "auth": {
        "requirement": "bearer",
        "loopbackBypass": true
      },
      "request": {
        "jsonSchema": {
          "$schema": "https://json-schema.org/draft/2020-12/schema",
          "type": "object",
          "properties": {
            "attachments": {
              "minItems": 1,
              "maxItems": 10,
              "type": "array",
              "items": {
                "type": "object",
                "properties": {
                  "name": {
                    "type": "string",
                    "minLength": 1
                  },
                  "mediaType": {
                    "type": "string",
                    "minLength": 1
                  },
                  "sizeBytes": {
                    "type": "number"
                  },
                  "data": {
                    "type": "string",
                    "minLength": 1
                  },
                  "kind": {
                    "type": "string",
                    "enum": ["image", "file"]
                  },
                  "originalPath": {
                    "type": "string"
                  }
                },
                "required": ["name", "mediaType", "data"]
              }
            }
          },
          "required": ["attachments"]
        },
        "source": "schemas.ts:UploadAttachmentsBody"
      },
      "response": {
        "envelope": "hand-rolled-json",
        "kinds": ["json"]
      },
      "statusCodes": [200, 400, 500],
      "sourceFile": "src/server/routes/attachments.ts",
      "confidence": "high"
    },
    {
      "method": "PATCH",
      "path": "/api/chats/:id/config",
      "auth": {
        "requirement": "bearer",
        "loopbackBypass": true
      },
      "request": {
        "jsonSchema": {
          "$schema": "https://json-schema.org/draft/2020-12/schema",
          "type": "object",
          "properties": {
            "adapterId": {
              "type": "string"
            },
            "model": {
              "type": "string"
            },
            "permissionMode": {
              "type": "string",
              "enum": ["default", "acceptEdits", "yolo"]
            },
            "planMode": {
              "type": "boolean"
            }
          }
        },
        "source": "ws-schemas.ts:UpdateChatConfigBody"
      },
      "response": {
        "envelope": "canonical-helpers",
        "kinds": ["envelope:fail", "envelope:ok"]
      },
      "statusCodes": [200, 400, 404, 500],
      "sourceFile": "src/server/routes/chat-commands.ts",
      "confidence": "high"
    },
    {
      "method": "GET",
      "path": "/api/chats/:id/context",
      "auth": {
        "requirement": "bearer",
        "loopbackBypass": true
      },
      "request": null,
      "response": {
        "envelope": "hand-rolled-json",
        "kinds": ["json"]
      },
      "statusCodes": [200, 404],
      "sourceFile": "src/server/routes/context.ts",
      "confidence": "high"
    },
    {
      "method": "POST",
      "path": "/api/chats/:id/disable-worktree",
      "auth": {
        "requirement": "bearer",
        "loopbackBypass": true
      },
      "request": null,
      "response": {
        "envelope": "canonical-helpers",
        "kinds": ["envelope:fail", "envelope:okEmpty"]
      },
      "statusCodes": [200, 400],
      "sourceFile": "src/server/routes/worktree.ts",
      "confidence": "high"
    },
    {
      "method": "PATCH",
      "path": "/api/chats/:id/effort",
      "auth": {
        "requirement": "bearer",
        "loopbackBypass": true
      },
      "request": {
        "name": "effortOnlySchema",
        "zodSource": "z.object({ effort: z.enum(EFFORT_VALUES).nullable() })",
        "source": "src/server/routes/chats.ts:effortOnlySchema",
        "note": "inline module-local Zod schema"
      },
      "response": {
        "envelope": "hand-rolled-json",
        "kinds": ["json"]
      },
      "statusCodes": [200, 400, 404, 500],
      "sourceFile": "src/server/routes/chats.ts",
      "confidence": "medium",
      "via": "delegated handler"
    },
    {
      "method": "POST",
      "path": "/api/chats/:id/enable-worktree",
      "auth": {
        "requirement": "bearer",
        "loopbackBypass": true
      },
      "request": {
        "name": "EnableWorktreeBody",
        "zodSource": "z.object({\n  baseBranch: z.string().min(1, 'Base branch is required'),\n  branchName: branchNameSchema,\n})",
        "source": "src/server/routes/worktree.ts:EnableWorktreeBody",
        "note": "inline module-local Zod schema"
      },
      "response": {
        "envelope": "canonical-helpers",
        "kinds": ["envelope:fail", "envelope:okEmpty"]
      },
      "statusCodes": [200, 400],
      "sourceFile": "src/server/routes/worktree.ts",
      "confidence": "medium"
    },
    {
      "method": "POST",
      "path": "/api/chats/:id/fork-worktree",
      "auth": {
        "requirement": "bearer",
        "loopbackBypass": true
      },
      "request": {
        "name": "ForkWorktreeBody",
        "zodSource": "z.object({\n  baseBranch: z.string().min(1, 'Base branch is required'),\n  branchName: branchNameSchema,\n})",
        "source": "src/server/routes/worktree.ts:ForkWorktreeBody",
        "note": "inline module-local Zod schema"
      },
      "response": {
        "envelope": "canonical-helpers",
        "kinds": ["envelope:fail", "envelope:ok"]
      },
      "statusCodes": [200, 400],
      "sourceFile": "src/server/routes/worktree.ts",
      "confidence": "medium"
    },
    {
      "method": "POST",
      "path": "/api/chats/:id/interrupt",
      "auth": {
        "requirement": "bearer",
        "loopbackBypass": true
      },
      "request": null,
      "response": {
        "envelope": "canonical-helpers",
        "kinds": ["envelope:fail", "envelope:okEmpty"]
      },
      "statusCodes": [200, 404, 500],
      "sourceFile": "src/server/routes/chat-commands.ts",
      "confidence": "high",
      "via": "command() wrapper"
    },
    {
      "method": "POST",
      "path": "/api/chats/:id/mentions",
      "auth": {
        "requirement": "bearer",
        "loopbackBypass": true
      },
      "request": {
        "jsonSchema": {
          "$schema": "https://json-schema.org/draft/2020-12/schema",
          "type": "object",
          "properties": {
            "kind": {
              "type": "string",
              "enum": ["file", "agent"]
            },
            "name": {
              "type": "string",
              "minLength": 1
            },
            "path": {
              "type": "string"
            }
          },
          "required": ["kind", "name"]
        },
        "source": "schemas.ts:AddMentionBody"
      },
      "response": {
        "envelope": "hand-rolled-json",
        "kinds": ["json"]
      },
      "statusCodes": [200, 400],
      "sourceFile": "src/server/routes/context.ts",
      "confidence": "high"
    },
    {
      "method": "GET",
      "path": "/api/chats/:id/messages",
      "auth": {
        "requirement": "bearer",
        "loopbackBypass": true
      },
      "request": null,
      "response": {
        "envelope": "hand-rolled-json",
        "kinds": ["json"]
      },
      "statusCodes": [200],
      "sourceFile": "src/server/routes/chats.ts",
      "confidence": "high"
    },
    {
      "method": "GET",
      "path": "/api/chats/:id/pending-permission",
      "auth": {
        "requirement": "bearer",
        "loopbackBypass": true
      },
      "request": {
        "name": "PendingPermissionParams",
        "zodSource": "z.object({ id: z.string().min(1) })",
        "source": "src/server/routes/chats.ts:PendingPermissionParams",
        "note": "inline module-local Zod schema"
      },
      "response": {
        "envelope": "hand-rolled-json",
        "kinds": ["json"]
      },
      "statusCodes": [200, 400],
      "sourceFile": "src/server/routes/chats.ts",
      "confidence": "medium"
    },
    {
      "method": "PATCH",
      "path": "/api/chats/:id/pinned",
      "auth": {
        "requirement": "bearer",
        "loopbackBypass": true
      },
      "request": {
        "name": "pinSchema",
        "zodSource": "z.object({ pinned: z.boolean() })",
        "source": "src/server/routes/chats.ts:pinSchema",
        "note": "inline module-local Zod schema"
      },
      "response": {
        "envelope": "hand-rolled-json",
        "kinds": ["json"]
      },
      "statusCodes": [200, 400, 404, 500],
      "sourceFile": "src/server/routes/chats.ts",
      "confidence": "medium"
    },
    {
      "method": "DELETE",
      "path": "/api/chats/:id/queue/:messageId",
      "auth": {
        "requirement": "bearer",
        "loopbackBypass": true
      },
      "request": null,
      "response": {
        "envelope": "canonical-helpers",
        "kinds": ["envelope:fail", "envelope:okEmpty"]
      },
      "statusCodes": [200, 404, 500],
      "sourceFile": "src/server/routes/chat-commands.ts",
      "confidence": "high",
      "via": "command() wrapper"
    },
    {
      "method": "PATCH",
      "path": "/api/chats/:id/queue/:messageId",
      "auth": {
        "requirement": "bearer",
        "loopbackBypass": true
      },
      "request": {
        "jsonSchema": {
          "$schema": "https://json-schema.org/draft/2020-12/schema",
          "type": "object",
          "properties": {
            "content": {
              "type": "string",
              "minLength": 1
            }
          },
          "required": ["content"]
        },
        "source": "ws-schemas.ts:QueueEditBody"
      },
      "response": {
        "envelope": "canonical-helpers",
        "kinds": ["envelope:fail", "envelope:okEmpty"]
      },
      "statusCodes": [200, 400, 404, 500],
      "sourceFile": "src/server/routes/chat-commands.ts",
      "confidence": "high"
    },
    {
      "method": "POST",
      "path": "/api/chats/:id/resume",
      "auth": {
        "requirement": "bearer",
        "loopbackBypass": true
      },
      "request": null,
      "response": {
        "envelope": "canonical-helpers",
        "kinds": ["envelope:fail", "envelope:okEmpty"]
      },
      "statusCodes": [200, 404, 500],
      "sourceFile": "src/server/routes/chat-commands.ts",
      "confidence": "high",
      "via": "command() wrapper"
    },
    {
      "method": "GET",
      "path": "/api/chats/:id/session-file",
      "auth": {
        "requirement": "bearer",
        "loopbackBypass": true
      },
      "request": null,
      "response": {
        "envelope": "hand-rolled-json",
        "kinds": ["envelope:fail", "envelope:ok", "json"]
      },
      "statusCodes": [200, 400, 403, 404],
      "sourceFile": "src/server/routes/context.ts",
      "confidence": "high"
    },
    {
      "method": "GET",
      "path": "/api/chats/:id/session-files",
      "auth": {
        "requirement": "bearer",
        "loopbackBypass": true
      },
      "request": null,
      "response": {
        "envelope": "canonical-helpers",
        "kinds": ["envelope:ok"]
      },
      "statusCodes": [200],
      "sourceFile": "src/server/routes/chats.ts",
      "confidence": "high"
    },
    {
      "method": "GET",
      "path": "/api/chats/:id/tags",
      "auth": {
        "requirement": "bearer",
        "loopbackBypass": true
      },
      "request": null,
      "response": {
        "envelope": "hand-rolled-json",
        "kinds": ["json"]
      },
      "statusCodes": [200],
      "sourceFile": "src/server/routes/tags.ts",
      "confidence": "high"
    },
    {
      "method": "PUT",
      "path": "/api/chats/:id/tags",
      "auth": {
        "requirement": "bearer",
        "loopbackBypass": true
      },
      "request": {
        "name": "SetChatTagsBody",
        "zodSource": "z.object({ tags: z.array(z.string()) })",
        "source": "src/server/routes/tags.ts:SetChatTagsBody",
        "note": "inline module-local Zod schema"
      },
      "response": {
        "envelope": "hand-rolled-json",
        "kinds": ["json"]
      },
      "statusCodes": [200, 400],
      "sourceFile": "src/server/routes/tags.ts",
      "confidence": "medium"
    },
    {
      "method": "PATCH",
      "path": "/api/chats/:id/title",
      "auth": {
        "requirement": "bearer",
        "loopbackBypass": true
      },
      "request": {
        "name": "titleSchema",
        "zodSource": "z.object({ title: z.string().trim().min(1) })",
        "source": "src/server/routes/chats.ts:titleSchema",
        "note": "inline module-local Zod schema"
      },
      "response": {
        "envelope": "hand-rolled-json",
        "kinds": ["json"]
      },
      "statusCodes": [200, 400, 404, 500],
      "sourceFile": "src/server/routes/chats.ts",
      "confidence": "medium"
    },
    {
      "method": "GET",
      "path": "/api/chats/:id/tool-result/:toolUseId",
      "auth": {
        "requirement": "bearer",
        "loopbackBypass": true
      },
      "request": {
        "name": "ToolResultParams",
        "zodSource": "z.object({\n    id: z.string().min(1),\n    toolUseId: z.string().regex(/^[a-zA-Z0-9_-]+$/),\n  })",
        "source": "src/server/routes/chats.ts:ToolResultParams",
        "note": "inline module-local Zod schema"
      },
      "response": {
        "envelope": "hand-rolled-json",
        "kinds": ["json"]
      },
      "statusCodes": [200, 400, 404],
      "sourceFile": "src/server/routes/chats.ts",
      "confidence": "medium"
    },
    {
      "method": "POST",
      "path": "/api/chats/:id/trust-workspace",
      "auth": {
        "requirement": "bearer",
        "loopbackBypass": true
      },
      "request": null,
      "response": {
        "envelope": "canonical-helpers",
        "kinds": ["envelope:fail", "envelope:okEmpty"]
      },
      "statusCodes": [200, 404, 500],
      "sourceFile": "src/server/routes/chat-commands.ts",
      "confidence": "high",
      "via": "command() wrapper"
    },
    {
      "method": "PATCH",
      "path": "/api/chats/:id/tuning",
      "auth": {
        "requirement": "bearer",
        "loopbackBypass": true
      },
      "request": {
        "name": "tuningSchema",
        "zodSource": "z.object({\n    effort: z.enum(EFFORT_VALUES).nullable().optional(),\n    fast: z.boolean().nullable().optional(),\n    ultracode: z.boolean().nullable().optional(),\n    adaptiveThinking: z.boolean().nullable().optional(),\n  })",
        "source": "src/server/routes/chats.ts:tuningSchema",
        "note": "inline module-local Zod schema"
      },
      "response": {
        "envelope": "hand-rolled-json",
        "kinds": ["json"]
      },
      "statusCodes": [200, 400, 404, 500],
      "sourceFile": "src/server/routes/chats.ts",
      "confidence": "medium",
      "via": "delegated handler"
    },
    {
      "method": "POST",
      "path": "/api/chats/:id/unarchive",
      "auth": {
        "requirement": "bearer",
        "loopbackBypass": true
      },
      "request": null,
      "response": {
        "envelope": "hand-rolled-json",
        "kinds": ["json"]
      },
      "statusCodes": [200, 404, 500],
      "sourceFile": "src/server/routes/chats.ts",
      "confidence": "high"
    },
    {
      "method": "GET",
      "path": "/api/commands",
      "auth": {
        "requirement": "bearer",
        "loopbackBypass": true
      },
      "request": null,
      "response": {
        "envelope": "hand-rolled-json",
        "kinds": ["json"]
      },
      "statusCodes": [200],
      "sourceFile": "src/server/routes/commands.ts",
      "confidence": "high"
    },
    {
      "method": "POST",
      "path": "/api/device/activity",
      "auth": {
        "requirement": "bearer",
        "loopbackBypass": true
      },
      "request": {
        "name": "ActivityBodySchema",
        "zodSource": "z.object({\n  state: z.enum(['active', 'idle']),\n})",
        "source": "src/server/routes/device.ts:ActivityBodySchema",
        "note": "inline module-local Zod schema"
      },
      "response": {
        "envelope": "hand-rolled-json",
        "kinds": ["json"]
      },
      "statusCodes": [200, 400],
      "sourceFile": "src/server/routes/device.ts",
      "confidence": "medium"
    },
    {
      "method": "GET",
      "path": "/api/files/external",
      "auth": {
        "requirement": "bearer",
        "loopbackBypass": true
      },
      "request": {
        "name": "ExternalFileQuery",
        "zodSource": "z.object({\n  path: z.string().min(1),\n})",
        "source": "src/server/routes/files.ts:ExternalFileQuery",
        "note": "inline module-local Zod schema"
      },
      "response": {
        "envelope": "canonical-helpers",
        "kinds": ["envelope:fail", "envelope:ok"]
      },
      "statusCodes": [200, 400, 403, 404, 413, 500],
      "sourceFile": "src/server/routes/files.ts",
      "confidence": "medium",
      "via": "delegated handler"
    },
    {
      "method": "GET",
      "path": "/api/filesystem/browse",
      "auth": {
        "requirement": "bearer",
        "loopbackBypass": true
      },
      "request": {
        "jsonSchema": {
          "$schema": "https://json-schema.org/draft/2020-12/schema",
          "type": "object",
          "properties": {
            "path": {
              "type": "string"
            },
            "includeFiles": {
              "anyOf": [
                {
                  "type": "boolean"
                },
                {
                  "type": "string",
                  "enum": ["true", "false"]
                }
              ]
            },
            "includeHidden": {
              "anyOf": [
                {
                  "type": "boolean"
                },
                {
                  "type": "string",
                  "enum": ["true", "false"]
                }
              ]
            }
          }
        },
        "source": "schemas.ts:BrowseFilesystemQuery"
      },
      "response": {
        "envelope": "canonical-helpers",
        "kinds": ["envelope:fail", "envelope:ok"]
      },
      "statusCodes": [200, 400, 404],
      "sourceFile": "src/server/routes/files.ts",
      "confidence": "high",
      "via": "delegated handler"
    },
    {
      "method": "POST",
      "path": "/api/git/commit",
      "auth": {
        "requirement": "bearer",
        "loopbackBypass": true
      },
      "request": {
        "name": "CommitBody",
        "zodSource": "z.object({\n  chatId: z.string(),\n  message: z.string().min(1, 'Commit message cannot be empty'),\n  files: z.array(z.string()),\n})",
        "source": "src/server/routes/git-chat.ts:CommitBody",
        "note": "inline module-local Zod schema"
      },
      "response": {
        "envelope": "canonical-helpers",
        "kinds": ["envelope:fail", "envelope:ok", "envelope:okEmpty"]
      },
      "statusCodes": [200, 400, 404, 409],
      "sourceFile": "src/server/routes/git-chat.ts",
      "confidence": "medium",
      "via": "delegated handler"
    },
    {
      "method": "POST",
      "path": "/api/git/push",
      "auth": {
        "requirement": "bearer",
        "loopbackBypass": true
      },
      "request": {
        "name": "PushBody",
        "zodSource": "z.object({ chatId: z.string() })",
        "source": "src/server/routes/git-chat.ts:PushBody",
        "note": "inline module-local Zod schema"
      },
      "response": {
        "envelope": "canonical-helpers",
        "kinds": ["envelope:fail", "envelope:ok", "envelope:okEmpty"]
      },
      "statusCodes": [200, 400, 404, 409],
      "sourceFile": "src/server/routes/git-chat.ts",
      "confidence": "medium",
      "via": "delegated handler"
    },
    {
      "method": "POST",
      "path": "/api/git/stage",
      "auth": {
        "requirement": "bearer",
        "loopbackBypass": true
      },
      "request": {
        "name": "StageBody",
        "zodSource": "z.object({ chatId: z.string(), files: z.array(z.string()) })",
        "source": "src/server/routes/git-chat.ts:StageBody",
        "note": "inline module-local Zod schema"
      },
      "response": {
        "envelope": "canonical-helpers",
        "kinds": ["envelope:fail", "envelope:ok", "envelope:okEmpty"]
      },
      "statusCodes": [200, 400, 404, 409],
      "sourceFile": "src/server/routes/git-chat.ts",
      "confidence": "medium",
      "via": "delegated handler"
    },
    {
      "method": "POST",
      "path": "/api/git/status",
      "auth": {
        "requirement": "bearer",
        "loopbackBypass": true
      },
      "request": {
        "name": "StatusBody",
        "zodSource": "z.object({ chatId: z.string() })",
        "source": "src/server/routes/git-chat.ts:StatusBody",
        "note": "inline module-local Zod schema"
      },
      "response": {
        "envelope": "canonical-helpers",
        "kinds": ["envelope:fail", "envelope:ok", "envelope:okEmpty"]
      },
      "statusCodes": [200, 400, 404, 409],
      "sourceFile": "src/server/routes/git-chat.ts",
      "confidence": "medium",
      "via": "delegated handler"
    },
    {
      "method": "POST",
      "path": "/api/git/unstage",
      "auth": {
        "requirement": "bearer",
        "loopbackBypass": true
      },
      "request": {
        "name": "StageBody",
        "zodSource": "z.object({ chatId: z.string(), files: z.array(z.string()) })",
        "source": "src/server/routes/git-chat.ts:StageBody",
        "note": "inline module-local Zod schema"
      },
      "response": {
        "envelope": "canonical-helpers",
        "kinds": ["envelope:fail", "envelope:ok", "envelope:okEmpty"]
      },
      "statusCodes": [200, 400, 404, 409],
      "sourceFile": "src/server/routes/git-chat.ts",
      "confidence": "medium",
      "via": "delegated handler"
    },
    {
      "method": "GET",
      "path": "/api/lsp/languages",
      "auth": {
        "requirement": "bearer",
        "loopbackBypass": true
      },
      "request": {
        "name": "LspLanguagesQuerySchema",
        "zodSource": "z.object({\n  projectId: z.string().min(1),\n})",
        "source": "src/server/routes/lsp-routes.ts:LspLanguagesQuerySchema",
        "note": "inline module-local Zod schema"
      },
      "response": {
        "envelope": "canonical-helpers",
        "kinds": ["envelope:fail", "envelope:ok"]
      },
      "statusCodes": [200, 400],
      "sourceFile": "src/server/routes/lsp-routes.ts",
      "confidence": "medium"
    },
    {
      "method": "GET",
      "path": "/api/projects",
      "auth": {
        "requirement": "bearer",
        "loopbackBypass": true
      },
      "request": null,
      "response": {
        "envelope": "hand-rolled-json",
        "kinds": ["json"]
      },
      "statusCodes": [200],
      "sourceFile": "src/server/routes/projects.ts",
      "confidence": "high"
    },
    {
      "method": "POST",
      "path": "/api/projects",
      "auth": {
        "requirement": "bearer",
        "loopbackBypass": true
      },
      "request": {
        "jsonSchema": {
          "$schema": "https://json-schema.org/draft/2020-12/schema",
          "type": "object",
          "properties": {
            "path": {
              "type": "string",
              "minLength": 1
            },
            "name": {
              "type": "string"
            }
          },
          "required": ["path"]
        },
        "source": "schemas.ts:CreateProjectBody"
      },
      "response": {
        "envelope": "hand-rolled-json",
        "kinds": ["json"]
      },
      "statusCodes": [200, 400, 409],
      "sourceFile": "src/server/routes/projects.ts",
      "confidence": "high"
    },
    {
      "method": "DELETE",
      "path": "/api/projects/:id",
      "auth": {
        "requirement": "bearer",
        "loopbackBypass": true
      },
      "request": null,
      "response": {
        "envelope": "hand-rolled-json",
        "kinds": ["json"]
      },
      "statusCodes": [200, 500],
      "sourceFile": "src/server/routes/projects.ts",
      "confidence": "high"
    },
    {
      "method": "GET",
      "path": "/api/projects/:id",
      "auth": {
        "requirement": "bearer",
        "loopbackBypass": true
      },
      "request": null,
      "response": {
        "envelope": "hand-rolled-json",
        "kinds": ["json"]
      },
      "statusCodes": [200, 404],
      "sourceFile": "src/server/routes/projects.ts",
      "confidence": "high"
    },
    {
      "method": "GET",
      "path": "/api/projects/:id/files",
      "auth": {
        "requirement": "bearer",
        "loopbackBypass": true
      },
      "request": null,
      "response": {
        "envelope": "canonical-helpers",
        "kinds": ["envelope:fail", "envelope:ok"]
      },
      "statusCodes": [200, 400, 403, 404, 413],
      "sourceFile": "src/server/routes/files.ts",
      "confidence": "high",
      "via": "delegated handler"
    },
    {
      "method": "PUT",
      "path": "/api/projects/:id/files",
      "auth": {
        "requirement": "bearer",
        "loopbackBypass": true
      },
      "request": {
        "name": "WriteFileBody",
        "zodSource": "z.object({\n  chatId: z.string().optional(),\n  path: z.string().min(1),\n  content: z.string(),\n})",
        "source": "src/server/routes/files.ts:WriteFileBody",
        "note": "inline module-local Zod schema"
      },
      "response": {
        "envelope": "canonical-helpers",
        "kinds": ["envelope:fail", "envelope:ok"]
      },
      "statusCodes": [200, 400, 403, 404, 500],
      "sourceFile": "src/server/routes/files.ts",
      "confidence": "medium",
      "via": "delegated handler"
    },
    {
      "method": "GET",
      "path": "/api/projects/:id/files-list",
      "auth": {
        "requirement": "bearer",
        "loopbackBypass": true
      },
      "request": null,
      "response": {
        "envelope": "canonical-helpers",
        "kinds": ["envelope:fail", "envelope:ok"]
      },
      "statusCodes": [200, 404],
      "sourceFile": "src/server/routes/files.ts",
      "confidence": "high",
      "via": "delegated handler"
    },
    {
      "method": "POST",
      "path": "/api/projects/:id/git/abort",
      "auth": {
        "requirement": "bearer",
        "loopbackBypass": true
      },
      "request": null,
      "response": {
        "envelope": "canonical-helpers",
        "kinds": ["envelope:fail", "envelope:ok", "envelope:okEmpty"]
      },
      "statusCodes": [200, 404, 500],
      "sourceFile": "src/server/routes/git-write.ts",
      "confidence": "high",
      "via": "delegated handler"
    },
    {
      "method": "GET",
      "path": "/api/projects/:id/git/branch",
      "auth": {
        "requirement": "bearer",
        "loopbackBypass": true
      },
      "request": null,
      "response": {
        "envelope": "canonical-helpers",
        "kinds": ["envelope:fail", "envelope:ok"]
      },
      "statusCodes": [200, 404],
      "sourceFile": "src/server/routes/git.ts",
      "confidence": "high",
      "via": "delegated handler"
    },
    {
      "method": "POST",
      "path": "/api/projects/:id/git/branch",
      "auth": {
        "requirement": "bearer",
        "loopbackBypass": true
      },
      "request": {
        "jsonSchema": {
          "$schema": "https://json-schema.org/draft/2020-12/schema",
          "type": "object",
          "properties": {
            "name": {
              "type": "string",
              "minLength": 1,
              "pattern": "^[a-zA-Z0-9][a-zA-Z0-9/_.-]*$"
            },
            "startPoint": {
              "type": "string"
            }
          },
          "required": ["name"]
        },
        "source": "schemas.ts:GitCreateBranchBody"
      },
      "response": {
        "envelope": "canonical-helpers",
        "kinds": ["envelope:fail", "envelope:ok", "envelope:okEmpty"]
      },
      "statusCodes": [200, 400, 404, 500],
      "sourceFile": "src/server/routes/git-write.ts",
      "confidence": "high",
      "via": "delegated handler"
    },
    {
      "method": "GET",
      "path": "/api/projects/:id/git/branch-diffs",
      "auth": {
        "requirement": "bearer",
        "loopbackBypass": true
      },
      "request": null,
      "response": {
        "envelope": "canonical-helpers",
        "kinds": ["envelope:fail", "envelope:ok"]
      },
      "statusCodes": [200, 404],
      "sourceFile": "src/server/routes/git.ts",
      "confidence": "high",
      "via": "delegated handler"
    },
    {
      "method": "GET",
      "path": "/api/projects/:id/git/branches",
      "auth": {
        "requirement": "bearer",
        "loopbackBypass": true
      },
      "request": null,
      "response": {
        "envelope": "canonical-helpers",
        "kinds": ["envelope:fail", "envelope:ok", "envelope:okEmpty"]
      },
      "statusCodes": [200, 404, 500],
      "sourceFile": "src/server/routes/git-write.ts",
      "confidence": "high",
      "via": "delegated handler"
    },
    {
      "method": "POST",
      "path": "/api/projects/:id/git/checkout",
      "auth": {
        "requirement": "bearer",
        "loopbackBypass": true
      },
      "request": {
        "jsonSchema": {
          "$schema": "https://json-schema.org/draft/2020-12/schema",
          "type": "object",
          "properties": {
            "branch": {
              "type": "string",
              "minLength": 1
            }
          },
          "required": ["branch"]
        },
        "source": "schemas.ts:GitCheckoutBody"
      },
      "response": {
        "envelope": "canonical-helpers",
        "kinds": ["envelope:fail", "envelope:ok", "envelope:okEmpty"]
      },
      "statusCodes": [200, 400, 404, 500],
      "sourceFile": "src/server/routes/git-write.ts",
      "confidence": "high",
      "via": "delegated handler"
    },
    {
      "method": "POST",
      "path": "/api/projects/:id/git/commit",
      "auth": {
        "requirement": "bearer",
        "loopbackBypass": true
      },
      "request": {
        "jsonSchema": {
          "$schema": "https://json-schema.org/draft/2020-12/schema",
          "type": "object",
          "properties": {
            "message": {
              "type": "string",
              "minLength": 1
            }
          },
          "required": ["message"]
        },
        "source": "schemas.ts:GitCommitBody"
      },
      "response": {
        "envelope": "canonical-helpers",
        "kinds": ["envelope:fail", "envelope:ok", "envelope:okEmpty"]
      },
      "statusCodes": [200, 400, 404, 500],
      "sourceFile": "src/server/routes/git-write.ts",
      "confidence": "high",
      "via": "delegated handler"
    },
    {
      "method": "POST",
      "path": "/api/projects/:id/git/delete-branch",
      "auth": {
        "requirement": "bearer",
        "loopbackBypass": true
      },
      "request": {
        "jsonSchema": {
          "$schema": "https://json-schema.org/draft/2020-12/schema",
          "type": "object",
          "properties": {
            "name": {
              "type": "string",
              "minLength": 1
            },
            "force": {
              "type": "boolean"
            },
            "remote": {
              "type": "boolean"
            }
          },
          "required": ["name"]
        },
        "source": "schemas.ts:GitDeleteBranchBody"
      },
      "response": {
        "envelope": "canonical-helpers",
        "kinds": ["envelope:fail", "envelope:ok", "envelope:okEmpty"]
      },
      "statusCodes": [200, 400, 404, 500],
      "sourceFile": "src/server/routes/git-write.ts",
      "confidence": "high",
      "via": "delegated handler"
    },
    {
      "method": "POST",
      "path": "/api/projects/:id/git/delete-worktree",
      "auth": {
        "requirement": "bearer",
        "loopbackBypass": true
      },
      "request": {
        "jsonSchema": {
          "$schema": "https://json-schema.org/draft/2020-12/schema",
          "type": "object",
          "properties": {
            "worktreePath": {
              "type": "string",
              "minLength": 1
            },
            "branchName": {
              "type": "string"
            }
          },
          "required": ["worktreePath"]
        },
        "source": "schemas.ts:GitDeleteWorktreeBody"
      },
      "response": {
        "envelope": "canonical-helpers",
        "kinds": ["envelope:fail", "envelope:okEmpty"]
      },
      "statusCodes": [200, 400, 404],
      "sourceFile": "src/server/routes/worktree.ts",
      "confidence": "high",
      "via": "delegated handler"
    },
    {
      "method": "GET",
      "path": "/api/projects/:id/git/diff",
      "auth": {
        "requirement": "bearer",
        "loopbackBypass": true
      },
      "request": {
        "name": "GitDiffQuery",
        "zodSource": "z.object({\n  chatId: z.string().optional(),\n  file: z.string().optional(),\n  oldPath: z.string().optional(),\n  // Validated (rejects a non-git source with 400) but not branched on — this\n  // endpoint only serves git, and the response hardcodes source: 'git'.\n  source: z.enum(['git']).optional(),\n  base: z.string().optional(),\n})",
        "source": "src/server/routes/git.ts:GitDiffQuery",
        "note": "inline module-local Zod schema"
      },
      "response": {
        "envelope": "canonical-helpers",
        "kinds": ["envelope:fail", "envelope:ok"]
      },
      "statusCodes": [200, 400, 403, 404],
      "sourceFile": "src/server/routes/git.ts",
      "confidence": "medium",
      "via": "delegated handler"
    },
    {
      "method": "POST",
      "path": "/api/projects/:id/git/diff-since-main",
      "auth": {
        "requirement": "bearer",
        "loopbackBypass": true
      },
      "request": {
        "name": "DiffSinceMainBody",
        "zodSource": "z.object({\n  chatId: z.string().optional(),\n  files: z.array(z.string()).optional(),\n})",
        "source": "src/server/routes/git-chat.ts:DiffSinceMainBody",
        "note": "inline module-local Zod schema"
      },
      "response": {
        "envelope": "canonical-helpers",
        "kinds": ["envelope:fail", "envelope:ok"]
      },
      "statusCodes": [200, 400, 404, 409],
      "sourceFile": "src/server/routes/git-chat.ts",
      "confidence": "medium",
      "via": "delegated handler"
    },
    {
      "method": "POST",
      "path": "/api/projects/:id/git/fetch",
      "auth": {
        "requirement": "bearer",
        "loopbackBypass": true
      },
      "request": {
        "jsonSchema": {
          "$schema": "https://json-schema.org/draft/2020-12/schema",
          "type": "object",
          "properties": {
            "remote": {
              "type": "string"
            }
          }
        },
        "source": "schemas.ts:GitFetchBody"
      },
      "response": {
        "envelope": "canonical-helpers",
        "kinds": ["envelope:fail", "envelope:ok", "envelope:okEmpty"]
      },
      "statusCodes": [200, 400, 404, 500],
      "sourceFile": "src/server/routes/git-write.ts",
      "confidence": "high",
      "via": "delegated handler"
    },
    {
      "method": "POST",
      "path": "/api/projects/:id/git/merge",
      "auth": {
        "requirement": "bearer",
        "loopbackBypass": true
      },
      "request": {
        "jsonSchema": {
          "$schema": "https://json-schema.org/draft/2020-12/schema",
          "type": "object",
          "properties": {
            "branch": {
              "type": "string",
              "minLength": 1
            }
          },
          "required": ["branch"]
        },
        "source": "schemas.ts:GitMergeBody"
      },
      "response": {
        "envelope": "canonical-helpers",
        "kinds": ["envelope:fail", "envelope:ok", "envelope:okEmpty"]
      },
      "statusCodes": [200, 400, 404, 500],
      "sourceFile": "src/server/routes/git-write.ts",
      "confidence": "high",
      "via": "delegated handler"
    },
    {
      "method": "POST",
      "path": "/api/projects/:id/git/pull",
      "auth": {
        "requirement": "bearer",
        "loopbackBypass": true
      },
      "request": {
        "jsonSchema": {
          "$schema": "https://json-schema.org/draft/2020-12/schema",
          "type": "object",
          "properties": {
            "remote": {
              "type": "string"
            },
            "branch": {
              "type": "string"
            },
            "localBranch": {
              "type": "string"
            }
          }
        },
        "source": "schemas.ts:GitPullBody"
      },
      "response": {
        "envelope": "canonical-helpers",
        "kinds": ["envelope:fail", "envelope:ok", "envelope:okEmpty"]
      },
      "statusCodes": [200, 400, 404, 500],
      "sourceFile": "src/server/routes/git-write.ts",
      "confidence": "high",
      "via": "delegated handler"
    },
    {
      "method": "POST",
      "path": "/api/projects/:id/git/push",
      "auth": {
        "requirement": "bearer",
        "loopbackBypass": true
      },
      "request": {
        "jsonSchema": {
          "$schema": "https://json-schema.org/draft/2020-12/schema",
          "type": "object",
          "properties": {
            "branch": {
              "type": "string"
            },
            "remote": {
              "type": "string"
            }
          }
        },
        "source": "schemas.ts:GitPushBody"
      },
      "response": {
        "envelope": "canonical-helpers",
        "kinds": ["envelope:fail", "envelope:ok", "envelope:okEmpty"]
      },
      "statusCodes": [200, 400, 404, 500],
      "sourceFile": "src/server/routes/git-write.ts",
      "confidence": "high",
      "via": "delegated handler"
    },
    {
      "method": "POST",
      "path": "/api/projects/:id/git/rebase",
      "auth": {
        "requirement": "bearer",
        "loopbackBypass": true
      },
      "request": {
        "jsonSchema": {
          "$schema": "https://json-schema.org/draft/2020-12/schema",
          "type": "object",
          "properties": {
            "branch": {
              "type": "string",
              "minLength": 1
            }
          },
          "required": ["branch"]
        },
        "source": "schemas.ts:GitRebaseBody"
      },
      "response": {
        "envelope": "canonical-helpers",
        "kinds": ["envelope:fail", "envelope:ok", "envelope:okEmpty"]
      },
      "statusCodes": [200, 400, 404, 500],
      "sourceFile": "src/server/routes/git-write.ts",
      "confidence": "high",
      "via": "delegated handler"
    },
    {
      "method": "POST",
      "path": "/api/projects/:id/git/rename-branch",
      "auth": {
        "requirement": "bearer",
        "loopbackBypass": true
      },
      "request": {
        "jsonSchema": {
          "$schema": "https://json-schema.org/draft/2020-12/schema",
          "type": "object",
          "properties": {
            "oldName": {
              "type": "string",
              "minLength": 1
            },
            "newName": {
              "type": "string",
              "minLength": 1,
              "pattern": "^[a-zA-Z0-9][a-zA-Z0-9/_.-]*$"
            }
          },
          "required": ["oldName", "newName"]
        },
        "source": "schemas.ts:GitRenameBranchBody"
      },
      "response": {
        "envelope": "canonical-helpers",
        "kinds": ["envelope:fail", "envelope:ok", "envelope:okEmpty"]
      },
      "statusCodes": [200, 400, 404, 500],
      "sourceFile": "src/server/routes/git-write.ts",
      "confidence": "high",
      "via": "delegated handler"
    },
    {
      "method": "GET",
      "path": "/api/projects/:id/git/status",
      "auth": {
        "requirement": "bearer",
        "loopbackBypass": true
      },
      "request": null,
      "response": {
        "envelope": "canonical-helpers",
        "kinds": ["envelope:fail", "envelope:ok"]
      },
      "statusCodes": [200, 404],
      "sourceFile": "src/server/routes/git.ts",
      "confidence": "high",
      "via": "delegated handler"
    },
    {
      "method": "POST",
      "path": "/api/projects/:id/git/update-all",
      "auth": {
        "requirement": "bearer",
        "loopbackBypass": true
      },
      "request": null,
      "response": {
        "envelope": "canonical-helpers",
        "kinds": ["envelope:fail", "envelope:ok", "envelope:okEmpty"]
      },
      "statusCodes": [200, 404, 500],
      "sourceFile": "src/server/routes/git-write.ts",
      "confidence": "high",
      "via": "delegated handler"
    },
    {
      "method": "GET",
      "path": "/api/projects/:id/git/working-stat",
      "auth": {
        "requirement": "bearer",
        "loopbackBypass": true
      },
      "request": null,
      "response": {
        "envelope": "canonical-helpers",
        "kinds": ["envelope:fail", "envelope:ok"]
      },
      "statusCodes": [200, 404, 500],
      "sourceFile": "src/server/routes/git.ts",
      "confidence": "high",
      "via": "delegated handler"
    },
    {
      "method": "GET",
      "path": "/api/projects/:id/git/worktrees",
      "auth": {
        "requirement": "bearer",
        "loopbackBypass": true
      },
      "request": null,
      "response": {
        "envelope": "canonical-helpers",
        "kinds": ["envelope:fail", "envelope:ok"]
      },
      "statusCodes": [200, 404],
      "sourceFile": "src/server/routes/worktree.ts",
      "confidence": "high"
    },
    {
      "method": "POST",
      "path": "/api/projects/:id/launch/:name/start",
      "auth": {
        "requirement": "bearer",
        "loopbackBypass": true
      },
      "request": null,
      "response": {
        "envelope": "hand-rolled-json",
        "kinds": ["json"]
      },
      "statusCodes": [200, 400, 404, 500],
      "sourceFile": "src/server/routes/launch.ts",
      "confidence": "high",
      "via": "delegated handler"
    },
    {
      "method": "POST",
      "path": "/api/projects/:id/launch/:name/stop",
      "auth": {
        "requirement": "bearer",
        "loopbackBypass": true
      },
      "request": null,
      "response": {
        "envelope": "hand-rolled-json",
        "kinds": ["json"]
      },
      "statusCodes": [200, 404],
      "sourceFile": "src/server/routes/launch.ts",
      "confidence": "high",
      "via": "delegated handler"
    },
    {
      "method": "GET",
      "path": "/api/projects/:id/launch/configs",
      "auth": {
        "requirement": "bearer",
        "loopbackBypass": true
      },
      "request": null,
      "response": {
        "envelope": "hand-rolled-json",
        "kinds": ["json"]
      },
      "statusCodes": [200, 400, 404],
      "sourceFile": "src/server/routes/launch.ts",
      "confidence": "high",
      "via": "delegated handler"
    },
    {
      "method": "GET",
      "path": "/api/projects/:id/launch/status",
      "auth": {
        "requirement": "bearer",
        "loopbackBypass": true
      },
      "request": null,
      "response": {
        "envelope": "hand-rolled-json",
        "kinds": ["json"]
      },
      "statusCodes": [200, 404],
      "sourceFile": "src/server/routes/launch.ts",
      "confidence": "high",
      "via": "delegated handler"
    },
    {
      "method": "GET",
      "path": "/api/projects/:id/paths/resolve",
      "auth": {
        "requirement": "bearer",
        "loopbackBypass": true
      },
      "request": {
        "name": "ResolvePathQuery",
        "zodSource": "z.object({\n  path: z.string().min(1),\n  chatId: z.string().optional(),\n})",
        "source": "src/server/routes/files.ts:ResolvePathQuery",
        "note": "inline module-local Zod schema"
      },
      "response": {
        "envelope": "canonical-helpers",
        "kinds": ["envelope:fail", "envelope:ok"]
      },
      "statusCodes": [200, 400, 404, 409],
      "sourceFile": "src/server/routes/files.ts",
      "confidence": "medium",
      "via": "delegated handler"
    },
    {
      "method": "GET",
      "path": "/api/projects/:id/search/content",
      "auth": {
        "requirement": "bearer",
        "loopbackBypass": true
      },
      "request": {
        "name": "ContentSearchQuery",
        "zodSource": "z.object({\n  q: z.string().min(2, 'Query must be at least 2 characters'),\n  path: z.string().min(1, 'path is required'),\n  chatId: z.string().optional(),\n  includeIgnored: z.string().optional(),\n})",
        "source": "src/server/routes/search.ts:ContentSearchQuery",
        "note": "inline module-local Zod schema"
      },
      "response": {
        "envelope": "canonical-helpers",
        "kinds": ["envelope:fail", "envelope:ok"]
      },
      "statusCodes": [200, 400, 403, 404, 500],
      "sourceFile": "src/server/routes/search.ts",
      "confidence": "medium",
      "via": "delegated handler"
    },
    {
      "method": "GET",
      "path": "/api/projects/:id/search/files",
      "auth": {
        "requirement": "bearer",
        "loopbackBypass": true
      },
      "request": null,
      "response": {
        "envelope": "canonical-helpers",
        "kinds": ["envelope:fail", "envelope:ok"]
      },
      "statusCodes": [200, 404],
      "sourceFile": "src/server/routes/files.ts",
      "confidence": "high",
      "via": "delegated handler"
    },
    {
      "method": "GET",
      "path": "/api/projects/:id/suggestions",
      "auth": {
        "requirement": "bearer",
        "loopbackBypass": true
      },
      "request": null,
      "response": {
        "envelope": "canonical-helpers",
        "kinds": ["envelope:fail", "envelope:ok"]
      },
      "statusCodes": [200, 404],
      "sourceFile": "src/server/routes/suggestions.ts",
      "confidence": "high",
      "via": "delegated handler"
    },
    {
      "method": "GET",
      "path": "/api/projects/:id/tree",
      "auth": {
        "requirement": "bearer",
        "loopbackBypass": true
      },
      "request": null,
      "response": {
        "envelope": "canonical-helpers",
        "kinds": ["envelope:fail", "envelope:ok"]
      },
      "statusCodes": [200, 403, 404],
      "sourceFile": "src/server/routes/files.ts",
      "confidence": "high",
      "via": "delegated handler"
    },
    {
      "method": "GET",
      "path": "/api/projects/:projectId/chats",
      "auth": {
        "requirement": "bearer",
        "loopbackBypass": true
      },
      "request": null,
      "response": {
        "envelope": "hand-rolled-json",
        "kinds": ["json"]
      },
      "statusCodes": [200],
      "sourceFile": "src/server/routes/chats.ts",
      "confidence": "high"
    },
    {
      "method": "GET",
      "path": "/api/projects/:projectId/external-sessions",
      "auth": {
        "requirement": "bearer",
        "loopbackBypass": true
      },
      "request": {
        "name": "listQuerySchema",
        "zodSource": "z.object({\n  offset: z.coerce.number().int().min(0).default(0),\n  limit: z.coerce.number().int().min(0).max(200).default(50),\n})",
        "source": "src/server/routes/external-sessions.ts:listQuerySchema",
        "note": "inline module-local Zod schema"
      },
      "response": {
        "envelope": "hand-rolled-json",
        "kinds": ["json"]
      },
      "statusCodes": [200, 400],
      "sourceFile": "src/server/routes/external-sessions.ts",
      "confidence": "medium"
    },
    {
      "method": "POST",
      "path": "/api/projects/:projectId/external-sessions/import",
      "auth": {
        "requirement": "bearer",
        "loopbackBypass": true
      },
      "request": {
        "name": "importBodySchema",
        "zodSource": "z.object({\n  sessionId: z.string().regex(/^[a-zA-Z0-9-]+$/),\n  adapterId: z.string().min(1),\n  title: z.string().max(500).optional(),\n  createdAt: z.string().datetime().optional(),\n  modifiedAt: z.string().datetime().optional(),\n})",
        "source": "src/server/routes/external-sessions.ts:importBodySchema",
        "note": "inline module-local Zod schema"
      },
      "response": {
        "envelope": "hand-rolled-json",
        "kinds": ["json"]
      },
      "statusCodes": [200, 400],
      "sourceFile": "src/server/routes/external-sessions.ts",
      "confidence": "medium"
    },
    {
      "method": "GET",
      "path": "/api/settings/general",
      "auth": {
        "requirement": "bearer",
        "loopbackBypass": true
      },
      "request": {
        "name": "ChatReadGroup",
        "zodSource": "z.object({ taskComplete: z.boolean(), sessionError: z.boolean() }).partial()",
        "source": "src/server/routes/settings.ts:ChatReadGroup",
        "note": "inline module-local Zod schema"
      },
      "response": {
        "envelope": "hand-rolled-json",
        "kinds": ["json"]
      },
      "statusCodes": [200],
      "sourceFile": "src/server/routes/settings.ts",
      "confidence": "medium",
      "via": "delegated handler"
    },
    {
      "method": "PUT",
      "path": "/api/settings/general",
      "auth": {
        "requirement": "bearer",
        "loopbackBypass": true
      },
      "request": {
        "jsonSchema": {
          "$schema": "https://json-schema.org/draft/2020-12/schema",
          "type": "object",
          "properties": {
            "worktreeDir": {
              "type": "string",
              "minLength": 1,
              "pattern": "^[a-zA-Z0-9._-]+$"
            },
            "notifications": {
              "type": "object",
              "properties": {
                "chat": {
                  "type": "object",
                  "properties": {
                    "taskComplete": {
                      "type": "boolean"
                    },
                    "sessionError": {
                      "type": "boolean"
                    }
                  }
                },
                "permission": {
                  "type": "object",
                  "properties": {
                    "toolRequest": {
                      "type": "boolean"
                    },
                    "userQuestion": {
                      "type": "boolean"
                    },
                    "planApproval": {
                      "type": "boolean"
                    }
                  }
                },
                "other": {
                  "type": "object",
                  "properties": {
                    "plugin": {
                      "type": "boolean"
                    }
                  }
                }
              }
            }
          }
        },
        "source": "schemas.ts:UpdateGeneralSettingsBody"
      },
      "response": {
        "envelope": "hand-rolled-json",
        "kinds": ["json"]
      },
      "statusCodes": [200, 400],
      "sourceFile": "src/server/routes/settings.ts",
      "confidence": "high",
      "via": "delegated handler"
    },
    {
      "method": "GET",
      "path": "/api/settings/providers",
      "auth": {
        "requirement": "bearer",
        "loopbackBypass": true
      },
      "request": null,
      "response": {
        "envelope": "hand-rolled-json",
        "kinds": ["json"]
      },
      "statusCodes": [200],
      "sourceFile": "src/server/routes/settings.ts",
      "confidence": "high"
    },
    {
      "method": "PUT",
      "path": "/api/settings/providers/:adapterId",
      "auth": {
        "requirement": "bearer",
        "loopbackBypass": true
      },
      "request": {
        "jsonSchema": {
          "$schema": "https://json-schema.org/draft/2020-12/schema",
          "type": "object",
          "properties": {
            "defaultModel": {
              "type": "string"
            },
            "defaultMode": {
              "type": "string",
              "enum": ["default", "acceptEdits", "yolo"]
            },
            "defaultPlanMode": {
              "type": "string",
              "enum": ["true", "false"]
            },
            "executablePath": {
              "type": "string"
            },
            "systemPrompt": {
              "type": "string"
            },
            "defaultEffort": {
              "type": "string",
              "enum": ["none", "minimal", "low", "medium", "high", "xhigh", "max", ""]
            },
            "defaultFast": {
              "type": "string",
              "enum": ["true", "false", ""]
            },
            "defaultUltracode": {
              "type": "string",
              "enum": ["true", "false", ""]
            },
            "defaultAdaptiveThinking": {
              "type": "string",
              "enum": ["true", "false", ""]
            },
            "personality": {
              "type": "string",
              "enum": ["none", "friendly", "pragmatic", ""]
            },
            "reasoningSummary": {
              "type": "string",
              "enum": ["auto", "concise", "detailed", "none", ""]
            }
          }
        },
        "source": "schemas.ts:UpdateProviderSettingsBody"
      },
      "response": {
        "envelope": "hand-rolled-json",
        "kinds": ["json"]
      },
      "statusCodes": [200, 400],
      "sourceFile": "src/server/routes/settings.ts",
      "confidence": "high"
    },
    {
      "method": "GET",
      "path": "/api/tags",
      "auth": {
        "requirement": "bearer",
        "loopbackBypass": true
      },
      "request": null,
      "response": {
        "envelope": "hand-rolled-json",
        "kinds": ["json"]
      },
      "statusCodes": [200],
      "sourceFile": "src/server/routes/tags.ts",
      "confidence": "high"
    },
    {
      "method": "POST",
      "path": "/api/tags",
      "auth": {
        "requirement": "bearer",
        "loopbackBypass": true
      },
      "request": {
        "name": "CreateBody",
        "zodSource": "z.object({ name: z.string(), color: ColorSchema.optional() })",
        "source": "src/server/routes/tags.ts:CreateBody",
        "note": "inline module-local Zod schema"
      },
      "response": {
        "envelope": "hand-rolled-json",
        "kinds": ["json"]
      },
      "statusCodes": [201, 400],
      "sourceFile": "src/server/routes/tags.ts",
      "confidence": "medium"
    },
    {
      "method": "DELETE",
      "path": "/api/tags/:name",
      "auth": {
        "requirement": "bearer",
        "loopbackBypass": true
      },
      "request": null,
      "response": {
        "envelope": "hand-rolled-json",
        "kinds": ["json", "no-body"]
      },
      "statusCodes": [204, 404],
      "sourceFile": "src/server/routes/tags.ts",
      "confidence": "high"
    },
    {
      "method": "PATCH",
      "path": "/api/tags/:name",
      "auth": {
        "requirement": "bearer",
        "loopbackBypass": true
      },
      "request": {
        "name": "PatchBody",
        "zodSource": "z\n  .object({ rename: z.string().optional(), color: ColorSchema.optional() })\n  .refine((v) => v.rename !== undefined || v.color !== undefined, {\n    message: 'rename or color required',\n  })",
        "source": "src/server/routes/tags.ts:PatchBody",
        "note": "inline module-local Zod schema"
      },
      "response": {
        "envelope": "hand-rolled-json",
        "kinds": ["json"]
      },
      "statusCodes": [200, 400, 404],
      "sourceFile": "src/server/routes/tags.ts",
      "confidence": "medium"
    },
    {
      "method": "GET",
      "path": "/api/tunnel/config",
      "auth": {
        "requirement": "bearer",
        "loopbackBypass": true
      },
      "request": null,
      "response": {
        "envelope": "hand-rolled-json",
        "kinds": ["json"]
      },
      "statusCodes": [200],
      "sourceFile": "src/server/routes/tunnel.ts",
      "confidence": "high"
    },
    {
      "method": "POST",
      "path": "/api/tunnel/start",
      "auth": {
        "requirement": "bearer",
        "loopbackBypass": true
      },
      "request": {
        "name": "TunnelStartBody",
        "zodSource": "z.object({\n  token: z.string().min(1).optional(),\n  url: z.url().optional(),\n})",
        "source": "src/server/routes/tunnel.ts:TunnelStartBody",
        "note": "inline module-local Zod schema"
      },
      "response": {
        "envelope": "hand-rolled-json",
        "kinds": ["json"]
      },
      "statusCodes": [200, 400, 500],
      "sourceFile": "src/server/routes/tunnel.ts",
      "confidence": "medium"
    },
    {
      "method": "GET",
      "path": "/api/tunnel/status",
      "auth": {
        "requirement": "bearer",
        "loopbackBypass": true
      },
      "request": null,
      "response": {
        "envelope": "hand-rolled-json",
        "kinds": ["json"]
      },
      "statusCodes": [200],
      "sourceFile": "src/server/routes/tunnel.ts",
      "confidence": "high"
    },
    {
      "method": "POST",
      "path": "/api/tunnel/stop",
      "auth": {
        "requirement": "bearer",
        "loopbackBypass": true
      },
      "request": {
        "name": "TunnelStopBody",
        "zodSource": "z.object({\n  clearConfig: z.boolean().optional(),\n})",
        "source": "src/server/routes/tunnel.ts:TunnelStopBody",
        "note": "inline module-local Zod schema"
      },
      "response": {
        "envelope": "hand-rolled-json",
        "kinds": ["json"]
      },
      "statusCodes": [200, 400],
      "sourceFile": "src/server/routes/tunnel.ts",
      "confidence": "medium"
    },
    {
      "method": "GET",
      "path": "/api/workflow-connectors",
      "auth": {
        "requirement": "bearer",
        "loopbackBypass": true
      },
      "request": null,
      "response": {
        "envelope": "canonical-helpers",
        "kinds": ["envelope:fail", "envelope:ok"]
      },
      "statusCodes": [200, 503],
      "sourceFile": "src/server/routes/workflow-admin.ts",
      "confidence": "high"
    },
    {
      "method": "GET",
      "path": "/api/workflow-credentials",
      "auth": {
        "requirement": "bearer",
        "loopbackBypass": true
      },
      "request": null,
      "response": {
        "envelope": "canonical-helpers",
        "kinds": ["envelope:fail", "envelope:ok"]
      },
      "statusCodes": [200, 503],
      "sourceFile": "src/server/routes/workflow-admin.ts",
      "confidence": "high"
    },
    {
      "method": "DELETE",
      "path": "/api/workflow-credentials/:label",
      "auth": {
        "requirement": "bearer",
        "loopbackBypass": true
      },
      "request": {
        "name": "LabelSchema",
        "zodSource": "z.string().regex(/^[a-zA-Z0-9_-]+$/)",
        "source": "src/server/routes/workflow-admin.ts:LabelSchema",
        "note": "inline module-local Zod schema"
      },
      "response": {
        "envelope": "canonical-helpers",
        "kinds": ["envelope:fail", "envelope:okEmpty"]
      },
      "statusCodes": [200, 400, 500, 503],
      "sourceFile": "src/server/routes/workflow-admin.ts",
      "confidence": "medium"
    },
    {
      "method": "PUT",
      "path": "/api/workflow-credentials/:label",
      "auth": {
        "requirement": "bearer",
        "loopbackBypass": true
      },
      "request": {
        "name": "CredentialBody",
        "zodSource": "z.object({ token: z.string() })",
        "source": "src/server/routes/workflow-admin.ts:CredentialBody",
        "note": "inline module-local Zod schema"
      },
      "response": {
        "envelope": "canonical-helpers",
        "kinds": ["envelope:fail", "envelope:okEmpty"]
      },
      "statusCodes": [200, 400, 500, 503],
      "sourceFile": "src/server/routes/workflow-admin.ts",
      "confidence": "medium"
    },
    {
      "method": "GET",
      "path": "/api/workflow-interactions",
      "auth": {
        "requirement": "bearer",
        "loopbackBypass": true
      },
      "request": null,
      "response": {
        "envelope": "canonical-helpers",
        "kinds": ["envelope:fail", "envelope:ok"]
      },
      "statusCodes": [200, 503],
      "sourceFile": "src/server/routes/workflow-admin.ts",
      "confidence": "high"
    },
    {
      "method": "POST",
      "path": "/api/workflow-interactions/:id/respond",
      "auth": {
        "requirement": "bearer",
        "loopbackBypass": true
      },
      "request": {
        "name": "RespondBody",
        "zodSource": "z.object({ response: z.record(z.string(), z.unknown()) })",
        "source": "src/server/routes/workflow-admin.ts:RespondBody",
        "note": "inline module-local Zod schema"
      },
      "response": {
        "envelope": "canonical-helpers",
        "kinds": ["envelope:fail", "envelope:okEmpty"]
      },
      "statusCodes": [200, 400, 404, 409, 503],
      "sourceFile": "src/server/routes/workflow-admin.ts",
      "confidence": "medium"
    },
    {
      "method": "GET",
      "path": "/api/workflow-runs/:runId",
      "auth": {
        "requirement": "bearer",
        "loopbackBypass": true
      },
      "request": null,
      "response": {
        "envelope": "canonical-helpers",
        "kinds": ["envelope:fail", "envelope:ok"]
      },
      "statusCodes": [200, 404, 503],
      "sourceFile": "src/server/routes/workflows.ts",
      "confidence": "high",
      "via": "delegated handler"
    },
    {
      "method": "POST",
      "path": "/api/workflow-runs/:runId/cancel",
      "auth": {
        "requirement": "bearer",
        "loopbackBypass": true
      },
      "request": null,
      "response": {
        "envelope": "canonical-helpers",
        "kinds": ["envelope:fail", "envelope:okEmpty"]
      },
      "statusCodes": [200, 404, 500, 503],
      "sourceFile": "src/server/routes/workflows.ts",
      "confidence": "high"
    },
    {
      "method": "GET",
      "path": "/api/workflows",
      "auth": {
        "requirement": "bearer",
        "loopbackBypass": true
      },
      "request": null,
      "response": {
        "envelope": "canonical-helpers",
        "kinds": ["envelope:fail", "envelope:ok"]
      },
      "statusCodes": [200, 503],
      "sourceFile": "src/server/routes/workflows.ts",
      "confidence": "high"
    },
    {
      "method": "DELETE",
      "path": "/api/workflows/:id",
      "auth": {
        "requirement": "bearer",
        "loopbackBypass": true
      },
      "request": null,
      "response": {
        "envelope": "canonical-helpers",
        "kinds": ["envelope:fail", "envelope:okEmpty"]
      },
      "statusCodes": [200, 404, 500, 503],
      "sourceFile": "src/server/routes/workflows.ts",
      "confidence": "high"
    },
    {
      "method": "GET",
      "path": "/api/workflows/:id",
      "auth": {
        "requirement": "bearer",
        "loopbackBypass": true
      },
      "request": null,
      "response": {
        "envelope": "canonical-helpers",
        "kinds": ["envelope:fail", "envelope:ok"]
      },
      "statusCodes": [200, 404, 503],
      "sourceFile": "src/server/routes/workflows.ts",
      "confidence": "high",
      "via": "delegated handler"
    },
    {
      "method": "PUT",
      "path": "/api/workflows/:id",
      "auth": {
        "requirement": "bearer",
        "loopbackBypass": true
      },
      "request": {
        "name": "WriteBody",
        "zodSource": "z.object({ yaml: z.string() })",
        "source": "src/server/routes/workflows.ts:WriteBody",
        "note": "inline module-local Zod schema"
      },
      "response": {
        "envelope": "canonical-helpers",
        "kinds": ["envelope:fail", "envelope:ok"]
      },
      "statusCodes": [200, 400, 404, 500, 503],
      "sourceFile": "src/server/routes/workflows.ts",
      "confidence": "medium",
      "via": "delegated handler"
    },
    {
      "method": "GET",
      "path": "/api/workflows/:id/runs",
      "auth": {
        "requirement": "bearer",
        "loopbackBypass": true
      },
      "request": null,
      "response": {
        "envelope": "canonical-helpers",
        "kinds": ["envelope:fail", "envelope:ok"]
      },
      "statusCodes": [200, 503],
      "sourceFile": "src/server/routes/workflows.ts",
      "confidence": "high"
    },
    {
      "method": "POST",
      "path": "/api/workflows/:id/runs",
      "auth": {
        "requirement": "bearer",
        "loopbackBypass": true
      },
      "request": {
        "name": "StartRunBody",
        "zodSource": "z.object({\n  inputs: z.record(z.string(), z.unknown()).optional(),\n  payload: z.unknown().optional(),\n})",
        "source": "src/server/routes/workflows.ts:StartRunBody",
        "note": "inline module-local Zod schema"
      },
      "response": {
        "envelope": "hand-rolled-json",
        "kinds": ["envelope:fail", "json"]
      },
      "statusCodes": [202, 400, 404, 503],
      "sourceFile": "src/server/routes/workflows.ts",
      "confidence": "medium"
    },
    {
      "method": "POST",
      "path": "/api/workflows/rescan",
      "auth": {
        "requirement": "bearer",
        "loopbackBypass": true
      },
      "request": null,
      "response": {
        "envelope": "canonical-helpers",
        "kinds": ["envelope:fail", "envelope:ok"]
      },
      "statusCodes": [200, 503],
      "sourceFile": "src/server/routes/workflows.ts",
      "confidence": "high"
    },
    {
      "method": "POST",
      "path": "/api/workflows/validate",
      "auth": {
        "requirement": "bearer",
        "loopbackBypass": true
      },
      "request": {
        "name": "ValidateBody",
        "zodSource": "z.object({ yaml: z.string() })",
        "source": "src/server/routes/workflows.ts:ValidateBody",
        "note": "inline module-local Zod schema"
      },
      "response": {
        "envelope": "canonical-helpers",
        "kinds": ["envelope:fail", "envelope:ok"]
      },
      "statusCodes": [200, 400, 500],
      "sourceFile": "src/server/routes/workflows.ts",
      "confidence": "medium"
    },
    {
      "method": "GET",
      "path": "/health",
      "auth": {
        "requirement": "none",
        "loopbackBypass": false
      },
      "request": null,
      "sourceFile": "src/server/http.ts",
      "statusCodes": [200],
      "envelope": "bare-json",
      "responseExample": {
        "status": "ok",
        "version": "<daemon version>",
        "timestamp": "<iso8601>",
        "tunnelUrl": "string|null"
      },
      "confidence": "high",
      "notes": "Unauthenticated health probe. Not the canonical envelope — bare object."
    }
  ]
}
